[
  {
    "title": "ट्रैफिक नियम उल्लंघकर्ताओं पर राजस्थान पुलिस का वज्रप्रहार; विशेष अभियान में अब तक हजारों वाहनों पर गाज, अकेले रविवार को नपे 7,721 वाहन•  सड़कों पर उतरा पुलिस का भारी अमला; काली फिल्म और अवैध हूटरों के खिलाफ जीरो टॉलरेंस",
    "state": "Rajasthan",
    "link": "https://dipr.rajasthan.gov.in/press-release-detail/243965/85",
    "content": "ट्रैफिक नियम उल्लंघकर्ताओं पर राजस्थान पुलिस का वज्रप्रहार; विशेष अभियान में अब तक हजारों वाहनों पर गाज, अकेले रविवार को नपे 7,721 वाहन\n•  सड़कों पर उतरा पुलिस का भारी अमला; काली फिल्म और अवैध हूटरों के खिलाफ जीरो टॉलरेंस\nवीआईपी श्रेणी वीआईपी व्यक्ति उप श्रेणी कार्यक्रम प्रेस विज्ञप्ति स्तर राज्य स्तरीय विभाग गृह विभाग जिला जिला जयपुर\nजयपुर 15 जून। राज्य में सड़क परिवहन को सुगम, सरल एवं सुरक्षित बनाने तथा मोटरयान अधिनियम के प्रावधानों का उल्लंघन करने वाले चालकों को कड़ा सबक सिखाने के लिए राजस्थान पुलिस का विशेष अभियान पूरी रफ्तार से चल रहा है।\nमहानिदेशक पुलिस श्री राजीव कुमार शर्मा के आदेशानुसार महानिदेशक पुलिस प्रशिक्षण एवं यातायात अनिल पालीवाल एवं अतिरिक्त महानिदेशक पुलिस यातायात डॉ. बी.एल. मीणा के कड़े पर्यवेक्षण में पूरे राज्य में 1 जून से 30 जून  तक यह सघन प्रवर्तन अभियान चलाया जा रहा है। रविवार को भी सबसे अधिक कार्रवाई ब्लैक फिल्म लगे वाहनों (2853) पर हुई, जो सड़क सुरक्षा एवं कानून व्यवस्था के लिए गंभीर चुनौती मानी जाती है।\nइसके तहत वाहनों में अवैध मॉडिफिकेशन, बिना अनुमति के लाल-नीली बत्ती, हूटर, प्रेशर हॉर्न, काली फिल्म (ब्लैक फिल्म), अनधिकृत शब्द और नियम विरुद्ध नंबर प्लेट लगाने वाले वाहनों के खिलाफ चौतरफा कार्रवाई जारी है, जो सड़क सुरक्षा के लिए गंभीर खतरा बने हुए हैं।\nएक ही दिन में 7,721 वाहनों पर कार्रवाई—\nअभियान के तहत 14 जून को अकेले पूरे राज्य में 7,721 वाहनों के खिलाफ कार्रवाई की गई। इनमें-\n°  726 वाहन अवैध संरचनात्मक परिवर्तन वाले,\n°  674 वाहन अनधिकृत लाल-नीली बत्ती एवं हूटर वाले,\n°  438 वाहन प्रेशर हॉर्न/एयर हॉर्न वाले,\n°  2,853 वाहन ब्लैक फिल्म लगे,\n°  1,041 वाहन अनधिकृत शब्द एवं चिन्ह प्रदर्शित करने वाले,\n°  1,989 वाहन नियम विरुद्ध नंबर प्लेट वाले पाए गए।\nकोटा शहर सबसे आगे\n14 जून की कार्रवाई में कोटा शहर 406 मामलों के साथ प्रदेश में प्रथम स्थान पर रहा। इसके बाद अलवर (388), जयपुर पश्चिम (378), जयपुर ग्रामीण (338) और जयपुर यातायात (303) प्रमुख रहे। वहीं चित्तौड़गढ़ (296) और भीलवाड़ा (297) में भी उल्लेखनीय कार्रवाई दर्ज की गई।\nसड़क सुरक्षा के लिए जारी रहेगा अभियान\nडीजे ट्रैफिक पालीवाल का कहना है कि सड़क दुर्घटनाओं को रोकने तथा सुरक्षित यातायात व्यवस्था सुनिश्चित करने के लिए यह विशेष चलाया जा रहा है। उन्होंन आमजन से अपील की है कि वे वाहनों में किसी भी प्रकार अवैध संशोधन, ब्लैक फिल्म, प्रेशर हॉर्न, अनधिकृत हूटर अथवा नियम विरुद्ध नंबर प्लेट का उपयोग न करें तथा यातायात नियमों का पालन कर स्वयं और दूसरों की सुरक्षा सुनिश्चित करे।\n------\nडॉ.कमलेश शर्मा/ब्रजेश\nडाउनलोड"
  },
  {
    "title": "युवा आपदा मित्र प्रशिक्षण में दिखा एसडीआरएफ का दम, एनसीसी कैडेट्स ने सीखे आपदा प्रबंधन के गुर—हार्ट अटैक, बाढ़ और सड़क हादसों में प्राथमिक उपचार का मिला व्यावहारिक प्रशिक्षण",
    "state": "Rajasthan",
    "link": "https://dipr.rajasthan.gov.in/press-release-detail/243964/85",
    "content": "युवा आपदा मित्र प्रशिक्षण में दिखा एसडीआरएफ का दम, एनसीसी कैडेट्स ने सीखे आपदा प्रबंधन के गुर—\nहार्ट अटैक, बाढ़ और सड़क हादसों में प्राथमिक उपचार का मिला व्यावहारिक प्रशिक्षण\nवीआईपी श्रेणी वीआईपी व्यक्ति उप श्रेणी कार्यक्रम प्रेस विज्ञप्ति स्तर राज्य स्तरीय विभाग गृह विभाग जिला जिला जयपुर\nजयपुर, 15 जून ।  महानिदेशक पुलिस श्री राजीव कुमार शर्मा के निर्देशानुसार राज्य आपदा प्रतिसाद बल (एसडीआरएफ) द्वारा संचालित सात दिवसीय युवा आपदा मित्र प्रशिक्षण कार्यक्रम के तहत सोमवार को एनसीसी कॉम्पलेक्स, जेएलएन मार्ग, गांधी नगर में एक विशेष जनजागरूकता कार्यक्रम, लाइव रेस्क्यू डेमो एवं आधुनिक आपदा राहत उपकरणों की प्रदर्शनी का आयोजन किया गया। कार्यक्रम का उद्देश्य युवाओं को आपदा प्रबंधन, राहत एवं बचाव कार्यों के प्रति प्रशिक्षित और जागरूक बनाना था।\nकार्यक्रम में 1 राजस्थान आर्म्ड स्क्वाड्रन एनसीसी के 57 स्वयंसेवकों (06 महिला एवं 51 पुरुष) ने भाग लिया, जो वर्तमान में एसडीआरएफ के माध्यम से सात दिवसीय युवा आपदा मित्र प्रशिक्षण प्राप्त कर रहे हैं।\nइस अवसर पर अतिरिक्त महानिदेशक पुलिस आरएसी एवं एसडीआरएफ श्री रूपिन्दर सिंघ ने आपदा प्रबंधन के महत्व पर प्रकाश डालते हुए कहा कि आपदा के समय प्रशिक्षित युवा समाज के लिए प्रथम प्रतिक्रिया दल की भूमिका निभा सकते हैं। वहीं डिप्टी डायरेक्टर जनरल एनसीसी एयर कॉमोडोर श्री सम्पत कुमार आनन्द ने आपदा के दौरान एनसीसी कैडेट्स की महत्वपूर्ण भूमिका और उनकी सामाजिक जिम्मेदारियों पर विस्तार से जानकारी दी।\nकार्यक्रम की शुरुआत महानिरीक्षक पुलिस आरएसी एवं एसडीआरएफ श्रीमती परम ज्योति के स्वागत उद्बोधन से हुई। उन्होंने युवाओं से आह्वान किया कि वे प्रशिक्षण के माध्यम से अर्जित कौशल का उपयोग समाज की सुरक्षा और सेवा में करें।\nरोप रेस्क्यू डेमो ने खींचा सबका ध्यान—\nएसडीआरएफ की विशेषज्ञ रेस्क्यू टीम ने परिसर में रोप रेस्क्यू डेमो प्रस्तुत कर ऊंचाई पर फंसे लोगों को सुरक्षित निकालने, दुर्घटनाग्रस्त व्यक्तियों को राहत पहुंचाने तथा विभिन्न आपदाओं में बचाव कार्यों की लाइव ड्रिल का प्रदर्शन किया। जवानों की दक्षता और समन्वय ने उपस्थित कैडेट्स एवं अधिकारियों को प्रभावित किया।\nहार्ट अटैक, बाढ़ और आग जैसी आपदाओं से निपटने का प्रशिक्षण\nजनजागरूकता कार्यक्रम में अचानक होने वाली घटनाओं जैसे हार्ट अटैक, सड़क दुर्घटना, बाढ़, गैस सिलेंडर में आग लगना आदि परिस्थितियों में प्रारंभिक सहायता एवं बचाव के व्यावहारिक तरीके बताए गए। प्रतिभागियों को यह भी समझाया गया कि रेस्क्यू टीमों के मौके पर पहुंचने से पहले आम नागरिक किस प्रकार घायलों और प्रभावित लोगों की मदद कर सकते हैं।\nआधुनिक रेस्क्यू उपकरणों की प्रदर्शनी बनी आकर्षण का केंद्र\nएसडीआरएफ द्वारा उपयोग किए जाने वाले आधुनिक राहत एवं बचाव उपकरणों की प्रदर्शनी भी लगाई गई, जहां कैडेट्स को उपकरणों की कार्यप्रणाली, उपयोगिता और आपदा प्रबंधन में उनकी भूमिका के बारे में विस्तार से जानकारी दी गई।\nकमांडेंट एसडीआरएफ श्री राजेन्द्र सिंह सिसोदिया ने एसडीआरएफ की संरचना, कार्यप्रणाली और राज्य में निभाई जा रही महत्वपूर्ण भूमिका पर प्रकाश डाला तथा कार्यक्रम के अंत में सभी अधिकारियों, प्रशिक्षकों और एनसीसी कैडेट्स का आभार व्यक्त किया।\nकार्यक्रम में ग्रुप कमांडर कर्नल सुरेश सिंधु (सेना मेडल), कमांडिंग ऑफिसर लेफ्टिनेंट कर्नल परमिंदर कौर, एनसीसी के अधिकारी एवं जवान, वार्षिक प्रशिक्षण प्राप्त कर रहे 326 कैडेट्स तथा जयपुर ग्रुप कैंप की छह इकाइयों से आए 82 अधिकारी एवं जवान भी उपस्थित रहे।\n----------------\nकमलेश शर्मा/ब्रजेश\nडाउनलोड"
  },
  {
    "title": "पुलिस महानिदेशक ने ली अपराध समीक्षा बैठक—झूठे मुकदमे कराने वालों पर कड़ी कार्रवाई के निर्देश—नशे की रोकथाम के लिए पुलिस अधीक्षक बनाएं कार्ययोजना—गैंगस्टरों की अवैध संपत्तियां ध्वस्त करने के निर्देश—- श्री राजीव कुमार शर्मा, पुलिस महानिदेशक",
    "state": "Rajasthan",
    "link": "https://dipr.rajasthan.gov.in/press-release-detail/243963/85",
    "content": "पुलिस महानिदेशक ने ली अपराध समीक्षा बैठक—\nझूठे मुकदमे कराने वालों पर कड़ी कार्रवाई के निर्देश—\nनशे की रोकथाम के लिए पुलिस अधीक्षक बनाएं कार्ययोजना—\nगैंगस्टरों की अवैध संपत्तियां ध्वस्त करने के निर्देश—\n- श्री राजीव कुमार शर्मा, पुलिस महानिदेशक\nवीआईपी श्रेणी वीआईपी व्यक्ति उप श्रेणी कार्यक्रम प्रेस विज्ञप्ति स्तर राज्य स्तरीय विभाग गृह विभाग जिला जिला जयपुर\nजयपुर, 15 जून। महानिदेशक पुलिस श्री राजीव कुमार शर्मा की अध्यक्षता में सोमवार को पुलिस मुख्यालय में वीडियो कॉन्फ्रेंसिंग के जरिए अपराध समीक्षा बैठक हुई। श्री शर्मा ने कहा कि प्रदेश की सुदृढ़ कानून-व्यवस्था ही विकसित राजस्थान की आधारशिला है। नवीन आपराधिक कानूनों के प्रभावी क्रियान्वयन से पुलिस पर जनविश्वास और अधिक मजबूत हुआ है। उन्होंने सक्रिय व संगठित अपराधों के विरुद्ध सख्त से सख्त कार्रवाई करने के निर्देश दिए। उन्होंने कहा कि झूठे मुकदमे दर्ज कराने वालों पर कड़ी कार्रवाई की जाए।\nपुलिस महानिदेशक ने समीक्षा बैठक में प्रदेश के पुलिस उच्चाधिकारियों को सम्बोधित किया। उन्होंने आपराधिक घटनाओं पर संबंधित रेंज आईजी व एसपी की कार्रवाई की जानकारी लेते हुए आवश्यक दिशा-निर्देश दिए। उन्होंने धमकी देकर वसूली करने वाले गिरोहों के विरुद्ध कठोर कार्रवाई करने और नवीन आपराधिक कानूनों के प्रावधानों के तहत अपराधियों की संपत्तियों को जब्त करने के निर्देश दिए। उन्होंने कहा कि गैंगस्टरों द्वारा अर्जित अवैध संपत्तियों को ध्वस्त करने की कार्रवाई सुनिश्चित की जाए। ऐसे अपराधियों के बैंक खातों सहित अन्य लेन-देन पर सतत निगरानी रखें।\nनशा तस्करों और साइबर अपराधियों पर करें प्रभावी कार्रवाई—\nश्री शर्मा ने पुलिस अधीक्षकों को नशा तस्करी और नशे के प्रसार पर प्रभावी अंकुश लगाने के लिए योजनाबद्ध अभियान चलाने के निर्देश दिए। साइबर अपराध, डिजिटल अरेस्ट और ऑनलाइन ठगी के मामलों में त्वरित कार्रवाई करते हुए अपराधियों तक पहुंच सुनिश्चित की जाए। उन्होंने पुलिस थानों में पुलिसकर्मियों को अनुसंधान के लिए नवीन तकनीकों का प्रशिक्षण दिलाने पर भी जोर दिया।\nपुलिस महानिदेशक ने कहा कि कानून एवं सुरक्षा से जुड़ी किसी भी संवेदनशील घटना की सूचना तत्काल उच्चाधिकारियों को दी जाए, ताकि समय पर मार्गदर्शन और आवश्यक सहयोग उपलब्ध कराया जा सके। पुराने प्रकरणों के शीघ्र निस्तारण एवं पीड़ितों को त्वरित न्याय दिलाने के भी निर्देश दिए गए।\nवर्षभर चलाए सड़क सुरक्षा जागरूकता अभियान—\nसड़क सुरक्षा की समीक्षा करते हुए पुलिस महानिदेशक ने कहा कि सड़क दुर्घटना केवल एक व्यक्ति नहीं बल्कि पूरे परिवार को प्रभावित करती है। उन्होंने राष्ट्रीय राजमार्गों और शहरी क्षेत्रों में लेन अनुशासन का शत-प्रतिशत पालन सुनिश्चित कराने तथा यातायात नियमों का उल्लंघन करने वालों के विरुद्ध सख्त प्रवर्तन कार्रवाई करने के निर्देश दिए। साथ ही सड़क सुरक्षा जागरूकता अभियान वर्षभर संचालित करने के निर्देश दिए।\nनीट परीक्षा के लिए दिए दिशा-निर्देश—\nश्री शर्मा ने नीट परीक्षा के सफल एवं शांतिपूर्ण आयोजन के लिए आवश्यक व्यवस्थाएं सुनिश्चित करने के निर्देश दिए। उन्होंने कहा कि सुव्यस्थित परीक्षा के लिए जारी दिशा-निर्देशों की अक्षरश पालना सुनिश्चित करें। सीसीटीवी के जरिए सतत निगरानी रखी जाए। समीक्षा बैठक में पुलिस मुख्यालय के वरिष्ठ अधिकारी मौजूद रहे।\n----\nडॉ.कमलेश शर्मा/ब्रजेश\nडाउनलोड"
  },
  {
    "title": "गिव अप अभियान ने 84 लाख लोगों की लौटाई मुस्कान, देशभर में हुई सराहना—खाद्य मंत्री श्री सुमित गोदारा ने हजारों लोगों की मौजूदगी में एनएफएसए लाभार्थियों से किया संवाद—श्रीडूंगरगढ़ के 30 हजार से अधिक वास्तविक लाभार्थियों को मिली राहत",
    "state": "Rajasthan",
    "link": "https://dipr.rajasthan.gov.in/press-release-detail/243962/85",
    "content": "गिव अप अभियान ने 84 लाख लोगों की लौटाई मुस्कान, देशभर में हुई सराहना—\nखाद्य मंत्री श्री सुमित गोदारा ने हजारों लोगों की मौजूदगी में एनएफएसए लाभार्थियों से किया संवाद—\nश्रीडूंगरगढ़ के 30 हजार से अधिक वास्तविक लाभार्थियों को मिली राहत\nवीआईपी श्रेणी कैबिनेट मंत्री वीआईपी व्यक्ति श्री सुमित गोदारा उप श्रेणी कार्यक्रम प्रेस विज्ञप्ति स्तर राज्य स्तरीय विभाग जिला बीकानेर जिला जिला बीकानेर, जिला जयपुर\nजयपुर, 15 जून। खाद्य एवं नागरिक आपूर्ति मंत्री श्री सुमित गोदारा ने सोमवार को बीकानेर के श्रीडूंगरगढ़ में एनएफएसए के लाभार्थियों से संवाद किया।\nपंचायत समिति परिसर में आयोजित कार्यक्रम के दौरान श्री गोदारा ने कहा कि गिव अप अभियान ने प्रदेश के 84 लाख लोगों की खोई मुस्कान लौटाई है। मुख्यमंत्री श्री भजनलाल शर्मा की अगुवाई में प्रदेश में चला यह अभियान देशभर के लिए नजीर बना। अभियान के तहत 82 लाख लोगों द्वारा स्वेच्छा से लाभ त्याग करना देशभर में नजीर है।\nश्री गोदारा ने कहा कि घर-घर संपर्क के दौरान यह सामने आया कि अपात्र लोग इस योजना का लाभ ले रहे थे जबकि पात्र एवं जरूरतमंद इससे वंचित हैं। खाद्य सुरक्षा अधि​नियम के अनुसार प्रदेश के 4.46 करोड़ लोगों को ही इसका लाभ दिया जा सकता था। उन्होंने कहा कि इसे ध्यान रखते हुए 1 नवंबर, 2024 को यह अभियान शुरू किया और सक्षम लोगों से स्वेच्छा से एनएफएसए का लाभ त्यागने का आह्वान किया। उन्होंने बताया कि अभियान से प्रेरित होकर 56 लाख ने इसका त्याग किया और 29 लाख ने ईकेवाईसी नहीं करवाई।\nउन्होंने बताया कि मुख्यमंत्री ने एक दशक से अधिक समय के बाद 26 जनवरी, 2025 को एनएफएसए पोर्टल चालू किया और अब तक 84 लाख वास्तविक पात्रजनों को लाभ दिया जा सका है। उन्होंने कहा कि इन लाभार्थियों को निःशुल्क इलाज, गैस सिलेंडर सब्सिडी और दुर्घटना में मृत्यु होने की स्थिति में परिजनों को पांच लाख रुपए तक की सहायता मिलेगी।\nप्रधानमंत्री के नेतृत्व में दस साल पूर्व चला ऐसा अभियान—\nश्री गोदारा ने कहा कि दस वर्ष पूर्व प्रधानमंत्री श्री नरेंद्र मोदी के नेतृत्व में गैस सब्सिडी स्वेच्छा के छोड़ने का अभियान चला। जिसे आमजन का बड़ा समर्थन मिला। गिव अप अभियान को भी आमजन का भरपूर सहयोग मिला है। उन्होंने कहा कि देश के गृह मंत्री श्री अमित शाह ने भी इसकी सराहना की। इस दौरान उन्होंने लाभार्थियों को खाद्य सुरक्षा प्रमाण पत्र प्रदान किए।\nजनप्रतिनिधियों में हो सकारात्मक प्रतिस्पर्धा की भावना—\nश्री गोदारा ने गत ढाई वर्षों में लूणकरणसर क्षेत्र में हुए विकास कार्यों के बारे में बताया और कहा कि इस अवधि में क्षेत्र में पानी, बिजली, सड़क, चिकित्सा, शिक्षा और पशु चिकित्सा के सहित सात प्रमुख क्षेत्रों में ऐतिहासिक कार्य हुए हैं। उन्होंने कहा कि आने वाले ढाई सालों में श्रीडूंगरगढ़ विधानसभा क्षेत्र प्रदेश के अग्रणी क्षेत्रों में शामिल होगा। श्री गोदारा ने कहा कि क्षेत्र के विकास के लिए जनप्रतिनिधियों में सकारात्मक प्रतिस्पर्धा होनी चाहिए।\nप्रत्येक क्षेत्र में लाभार्थियों से हो रहा संवाद—\nश्री गोदारा ने कहा कि प्रदेश में चले ऐतिहासिक गिव अप अभियान की सफलता के पश्चात मुख्यमंत्री ने विभिन्न क्षेत्रों के एनएफएसए लाभार्थियों के साथ संवाद करने के निर्देश दिए हैं। इसकी अनुपालना में अब तक नोखा और खाजूवाला में लाभार्थी सम्मेलन आयोजित किया जा चुका है। भविष्य में अन्य विधानसभाओं में भी इसका आयोजन किया जाएगा। उन्होंने बताया कि श्रीडूंगरगढ़ में 34 लाख लोगों ने स्वेच्छा से एनएफएसए का लाभ छोड़ा है, जिससे 30 हजार से अधिक पात्र लोगों को योजना से जोड़कर राहत दी गई है।\nश्रीडूंगरगढ़ विधायक श्री ताराचंद सारस्वत ने कहा कि गत ढाई वर्षों में क्षेत्र ने विकास के नए कीर्तिमान स्थापित किए हैं। क्षेत्र में सड़क, पानी, विद्युत तंत्र सुदृढ़ीकरण सहित आधारभूत सुविधाओं का विकास तेजी से हो रहा है। उन्होंने कहा कि क्षेत्र के प्रत्येक गांव में बड़ी संख्या में ट्रांसफार्मर लगे हैं। जिससे विद्युत तंत्र में आमूलचूल सुधार हुआ है।\nश्री विश्वकर्मा कौशल विकास बोर्ड के अध्यक्ष श्री राम गोपाल सुथार ने कहा कि केंद्र और राज्य सरकार मजदूरों, गरीबों, महिलाओं, वृद्धजनों और किसानों के कल्याण के लिए प्रतिबद्ध है। सरकार की अनेक योजनाएं इन वर्गों के लिए चलाई जा रही हैं। पात्र व्यक्ति इनका लाभ उठाएं, उन्होंने शहरी और ग्रामीण सेवा शिविरों में अधिक से अधिक लोगों को पहुंचाने का आह्वान किया।\nइस दौरान श्री जालम सिंह भाटी, श्री रामेश्वर पारीक और श्री छैलू सिंह शेखावत ने भी विचार रखे। कार्यक्रम में श्री मानमल शर्मा, श्री विनोद गिरी गुसाई, श्री महेंद्रनाथ तंवर, श्री कानाराम, श्री राजकुमार कस्वा, श्री हेमनाथ जाखड़ सहित बड़ी संख्या में ग्रामीण मौजूद रहे। कार्यक्रम के दौरान अनेक लोगों ने मंत्री श्री गोदारा का मालाएं पहनाकर स्वागत किया।\nबीकानेर से श्रीडूंगरगढ़ के बीच दर्जनों स्थानों पर हुआ अभिनन्दन—\nइससे पहले बीकानेर से रवाना होने पर खाद्य एवं नागरिक आपूर्ति मंत्री श्री सुमित गोदारा का रायसर, सेरूणा, झंझेउ, जोधासर और लखासर सहित श्रीडूंगरगढ़ तक दर्जनों स्थानों पर भव्य स्वागत हुआ। बड़ी संख्या में लोगों ने की मंत्री श्री गोदारा की अगवानी की। इनमें सेरूणा से पूर्व सरपंच, श्री  रणवीर सिंह, श्री गौरीशंकर स्वामी, श्री श्रीभगवान स्वामी, झंझेउ से श्री भँवर सिंह तंवर, रीडी से श्री बालू राम जाखड़, श्री मुनीराम जाखड़, बादनूं से श्री नवरत्न घिंटाला, लखासर से श्री भंवर सिंह चंद्रावत, गोपालसर से श्री सीताराम बुढ़िया, श्री कुलदीप सारस्वत सहित अनेक जनप्रतिनिधि शामिल रहे।\n—————\nहरिशंकर/ब्रजेश\nडाउनलोड"
  },
  {
    "title": "बारिश से पूर्व नालों की सफाई, पेचवर्क और मरम्मत का काम पूरा हो-श्री देवनानीविधानसभा अध्यक्ष ने एडीए, नगर निगम व पीडब्ल्यूडी के अधिकारियों की बैठक लेकर शहर की सफाई, जलभराव का समाधान एवं अन्य मुद्दों पर हुई चर्चा—माकड़वाली रोड़ पर मरम्मत होगी, एडीए को सौंपी जाएगी सड़क",
    "state": "Rajasthan",
    "link": "https://dipr.rajasthan.gov.in/press-release-detail/243959/85",
    "content": "बारिश से पूर्व नालों की सफाई, पेचवर्क और मरम्मत का काम पूरा हो-श्री देवनानी\nविधानसभा अध्यक्ष ने एडीए, नगर निगम व पीडब्ल्यूडी के अधिकारियों की बैठक लेकर शहर की सफाई, जलभराव का समाधान एवं अन्य मुद्दों पर हुई चर्चा—\nमाकड़वाली रोड़ पर मरम्मत होगी, एडीए को सौंपी जाएगी सड़क\nवीआईपी श्रेणी अध्यक्ष, राज सभा वीआईपी व्यक्ति श्री वासुदेव देवनानी उप श्रेणी रिलीज़ प्रेस विज्ञप्ति स्तर राज्य स्तरीय विभाग राजस्थान विधान सभा जिला जिला जयपुर\nजयपुर, 15 जून। विधानसभा अध्यक्ष श्री वासुदेव देवनानी ने आगामी दिनों में बारिश से पूर्व अजमेर शहर में सभी आवश्यक व्यवस्थाएं सुनिश्चित करने के निर्देश दिए हैं। नगर निगम बारिश से पूर्व नालों की शत-प्रतिशत सफाई करवा लें ताकि पानी की निकासी में अवरोध नहीं आए। निगम, एडीए और पीडब्ल्यूडी सड़कों के गड्ढे भरने, मरम्मत और पेचवर्क के काम आगामी 15 दिनों में पूरा कर लें। माकड़वाली रोड़ पर मरम्मत से संबंधित कार्य सार्वजनिक निर्माण विभाग शीघ्र करवा कर एडीए को सड़क सौंपेगा। जल भराव में बचाव के लिए पर्याप्त मात्रा में पम्प तैयार रखे जाए।\nविधानसभा अध्यक्ष ने सोमवार को सर्किट हाउस में अजमेर विकास प्राधिकरण, नगर निगम, सार्वजनिक निर्माण विभाग से संबंधित कामकाज एवं बारिश से पूर्व की जाने वाली तैयारियों की समीक्षा की। जिला कलक्टर श्री लोक बन्धु एवं आयुक्त श्रीमती नित्या के. भी बैठक में उपस्थित रहें। बैठक में श्री देवनानी ने कहा कि आगामी कुछ दिनों में मानसून सक्रिय हो जाएगा। सभी संबंधित विभाग अपनी तैयारी पूरी कर लें। मानसून से पूर्व नालों की सफाई सुनिश्चित की जाए। नगर निगम शत-प्रतिशत नालों की सफाई करवाएं। निगम, एडीए और पीडब्ल्यूडी समन्वय स्थापित कर सड़कों की मरम्मत, पेचवर्क और अन्य कार्य करवाएं। बारिश ज्यादा होने पर कुछ क्षेत्रों में जलभराव से बचाव के लिए आवश्यक मात्रा में बड़े पम्प व मड पम्प तैनात रखे जाएं।\nबैठक में माकड़वाली रोड़ पर सुधार के लिए चर्चा की गई। सार्वजनिक निर्माण विभाग क्षतिग्रस्त सड़क की मरम्मत करवा कर शीघ्र एडीए को हैंडओवर करेगा। इसे बाद सड़क की देखरेख का जिम्मा एडीए संभालेगा। इसी तरह अन्य सड़कों के हैंडओवर व देखरेख पर भी चर्चा की गई।\nबैठक में श्री देवनानी ने अजमेर शहर में जल भराव से मुक्ति के लिए 150 करोड़ रूपए के डे्रनेज प्लान पर भी चर्चा की। उन्होंने कहा कि इन प्रस्तावों को शीघ्र तैयार किया जाए। इसी तरह डी-सिल्टिंग के विषय पर भी सिंचाई विभाग को त्वरित गति से काम करने के निर्देश दिए गए। सार्वजनिक निर्माण विभाग को निर्देश दिए गए कि पुष्कर घाटी में भारी वाहनों का प्रवेश रोकने के लिए हाइट बैरियर जल्द लगाने के निर्देश दिए गए। जयपुर रोड़ पर अजमेर प्रवेश द्वारा के पास जल भराव की समस्या के समाधान के लिए एडीए आवश्यक इंतजाम करेगा। विवेकानन्द पार्क में आध्यात्मिक केन्द्र की स्थापना के लिए कार्य में गति लाने के निर्देश भी दिए गए।\nबैठक में श्री देवननी ने नगर निगम गौशाला प्रबंधन, सरकारी भूमि में अतिक्रमण हटाने, विधायक कोष के कार्य, तारागढ़उ विकास सहित अन्य विषयों पर चर्चा की। बैठक में जिला कलक्टर श्री लोक बन्धु ने कहा कि सभी विभाग आपसी समन्वय स्थापित कर काम करें। बारिश के दिनों में अलर्ट मोड पर रह कर काम करें। आमजन को शहरी एवं ग्रामीण सेवा शिविरों का अधिक लाभ प्रदान करें।\nबैठक में एडीए सचिव श्री अनिल पूनिया, सार्वजनिक निर्माण विभाग के अधीक्षण अभियंता श्री अशोक तंवर सहित अन्य अधिकारी उपस्थित रहे।\n——————\nभानु प्रताप/ब्रजेश\nडाउनलोड"
  },
  {
    "title": "सेई बांध टनल विस्तार : अब  बेकार बहकर गुजरात नहीं जाएगा पानी- पश्चिमी राजस्थान के 3 जिलों को मिलेगा भरपूर जल- पशुपालन मंत्री श्री जोराराम कुमावत ने किया टनल के निर्माण कार्य का निरीक्षण",
    "state": "Rajasthan",
    "link": "https://dipr.rajasthan.gov.in/press-release-detail/243958/85",
    "content": "सेई बांध टनल विस्तार : अब  बेकार बहकर गुजरात नहीं जाएगा पानी\n- पश्चिमी राजस्थान के 3 जिलों को मिलेगा भरपूर जल\n- पशुपालन मंत्री श्री जोराराम कुमावत ने किया टनल के निर्माण कार्य का निरीक्षण\nवीआईपी श्रेणी वीआईपी व्यक्ति उप श्रेणी निरीक्षण प्रेस विज्ञप्ति स्तर राज्य स्तरीय विभाग पशुपालन विभाग जिला जिला जयपुर, जिला उदयपुर\nजयपुर, 15 जून। पशुपालन मंत्री श्री जोराराम कुमावत ने सोमवार को उदयपुर जिले के कोटड़ा का दौरा किया। उन्होंने जल संसाधन विभाग के अधिकारियों के साथ बहुप्रतीक्षित सेई बांध की टनल (सुरंग) की चौड़ाई बढ़ाने के चल रहे निर्माण कार्यों का बारीकी से निरीक्षण किया। श्री कुमावत ने टनल के भीतर जाकर निर्माण कार्य की प्रगति देखी और अधिकारियों से अब तक हुए कार्य, बची हुई खुदाई और कंक्रीट लाइनिंग के तकनीकी पहलुओं की विस्तृत जानकारी ली।\nयोजना के लिए ₹100 करोड़ का बजट, 95% काम पूरा—\nश्री कुमावत ने बताया कि सेई बांध से अतिरिक्त पानी को जवाई बांध तक पहुँचाने के लिए बनी 6.7 किलोमीटर लंबी सुरंग को चौड़ा करने के लिए सरकार ने बजट में कुल ₹100 करोड़ का प्रावधान किया है। पिछले तीन साल से चल रहे इस कार्य का करीब 95 फीसदी हिस्सा पूरा हो चुका है। अब केवल 90 मीटर टनल का कार्य बाकी है, जिसे आगामी 15 जुलाई तक हर हाल में पूरा करने के कड़े निर्देश दिए गए हैं। उन्होंने बताया कि पश्चिमी राजस्थान के जल संकट को दूर करने के लिए बड़े स्तर पर कार्य किया जा रहा है और निर्माण की गुणवत्ता में किसी भी प्रकार का समझौता बर्दाश्त नहीं होगा। साथ ही, उन्होंने टनल के अंदर काम कर रहे श्रमिकों और इंजीनियरों की सुरक्षा के पुख्ता इंतजाम रखने की हिदायत दी।\nजल निकासी क्षमता होगी 4 गुना, 22 दिन में भरेगा जवाई बांध—\nश्री कुमावत ने बताया कि इस टनल का विस्तार होने से पानी की निकासी क्षमता 328 क्यूसेक से बढ़कर 1376 क्यूसेक हो जाएगी। 4 गुना  क्षमता बढ़ने से मानसून के दौरान अतिरिक्त पानी व्यर्थ बहकर गुजरात नहीं जाएगा। इससे पाली, सिरोही और जालोर जिलों को भरपूर पानी मिल सकेगा। उन्होंने आगे बताया कि वर्तमान में टनल की चौड़ाई कम होने के कारण सेई बांध से जवाई बांध तक पानी पहुँचने में 45 से 50 दिन का समय लगता है लेकिन यह कार्य पूरा होने के बाद मात्र 22 दिन में ही जवाई बांध को 74 एमसीएफटी पानी मिलने लगेगा, जो इस क्षेत्र के लिए एक बड़ी राहत साबित होगा।\nमारवाड़ के लिए संजीवनी है यह परियोजना—\nसेई बांध और इसकी टनल मारवाड़ क्षेत्र विशेषकर पाली जिले के लिए जीवनदायिनी मानी जाती है। कोटड़ा के सेई बांध से पानी को इस टनल के जरिए जवाई बांध में डाइवर्ट किया जाता है। जवाई बांध पाली और जोधपुर के कई इलाकों की प्यास बुझाता है। वर्तमान में टनल की क्षमता कम होने के कारण मानसून के दौरान सेई बांध का अतिरिक्त पानी बहकर गुजरात चला जाता है। टनल की चौड़ाई बढ़ने से पानी का प्रवाह (डिस्चार्ज क्षमता) तेजी से बढ़ेगा। मानसून का अतिरिक्त पानी व्यर्थ बहने से बचेगा। जवाई बांध कम समय में और अधिक मात्रा में भरा जा सकेगा। पाली सहित पूरे मारवाड़ क्षेत्र में पेयजल और सिंचाई संकट का स्थाई समाधान होगा।\nइको-टूरिज्म और सौंदर्यकरण योजना—\nश्री कुमावत ने कहा कि अब इस बांध क्षेत्र को इको-टूरिज्म और स्थानीय पर्यटन केंद्र के रूप में भी विकसित करने की योजना बनाई जा रही है। इसके तहत बांध की प्राकृतिक सुंदरता का उपयोग कर पर्यटकों के लिए बुनियादी सुविधाओं का विस्तार किया जाएगा। इस दौरान किसान संघर्ष समिति के अध्यक्ष श्री जयेंद्र सिंह गलथनी, श्री अनोप सिंह राठौड़, श्री पूनम सिंह परमार, निम्बेश्वर महादेव ट्रस्ट के अध्यक्ष श्री जगत सिंह, श्री शिवराज सिंह बिठिया, श्री रविकांत रावल भी मौजूद रहे।\n———————\nब्रजेश\nडाउनलोड"
  },
  {
    "title": "शहीद अग्निवीरवायु श्री खेमाराम कुमावत का पैतृक गांव पांचौता में अंतिम संस्कार—राज्यमंत्री श्री विजय सिंह चौधरी व जिला कलक्टर समेत हजारों ने नम आंखों से दी श्रद्धांजलि, अर्पित किये पुष्पचक्र",
    "state": "Rajasthan",
    "link": "https://dipr.rajasthan.gov.in/press-release-detail/243957/85",
    "content": "शहीद अग्निवीरवायु श्री खेमाराम कुमावत का पैतृक गांव पांचौता में अंतिम संस्कार—\nराज्यमंत्री श्री विजय सिंह चौधरी व जिला कलक्टर समेत हजारों ने नम आंखों से दी श्रद्धांजलि, अर्पित किये पुष्पचक्र\nवीआईपी श्रेणी माननीय  राज्य मंत्री वीआईपी व्यक्ति श्री विजय सिंह उप श्रेणी रिलीज़ प्रेस विज्ञप्ति स्तर राज्य स्तरीय विभाग जिला डीडवाना-कुचामन जिला जिला जयपुर, जिला डीडवाना-कुचामन\nजयपुर, 15 जून। असम के जोरहाट में भारतीय वायु सेना के एएन-32 विमान हादसे में शहीद हुए अग्निवीरवायु श्री खेमाराम कुमावत का सोमवार को राजकीय सम्मान के साथ डीडवाना-कुचामन स्थित उनके पैतृक गांव नावां उपखंड के पांचौता में अंतिम संस्कार हुआ। इस अवसर पर राजस्व एवं सैनिक कल्याण राज्यमंत्री श्री विजय सिंह चौधरी, जिला कलक्टर श्री अवधेश मीना ने शहीद के पार्थिव शरीर पर नम आंखों से पुष्पचक्र अर्पित कर भावभीनी श्रद्धांजलि दी।\nश्रद्धांजलि अर्पित करते हुए जनप्रतिनिधियों एवं प्रशासनिक अधिकारियों ने शहीद श्री खेमाराम कुमावत के अदम्य साहस, राष्ट्रसेवा के प्रति समर्पण एवं सर्वोच्य बलिदान को नमन किया तथा शोक संतप्त परिजनों के प्रति संवेदना व्यक्त की।\nराज्यमंत्री श्री विजय सिंह चौधरी ने कहा कि शहीद श्री खेमाराम कुमावत ने मातृभूमि की रक्षा करते हुए अपना  सर्वोच्च  बलिदान दिया है। उनका त्याग और समर्पण सदैव देशवासियों को राष्ट्रसेवा के लिए प्रेरित करता रहेगा।\nइससे पूर्व उनका पार्थिव शरीर सोमवार को विशेष विमान से जयपुर एयरपोर्ट लाया गया। इसके पश्चात शहीद का पार्थिव शरीर सड़क मार्ग से डीडवाना-कुचामन स्थित उनके पैतृक गांव नावां उपखंड के पांचौता पहुँचा।\n——————\nअभिमन्यु/ब्रजेश\nडाउनलोड"
  },
  {
    "title": "राजस्व मंत्री श्री हेमंत मीणा एवं सांसद श्री सीपी जोशी ने प्रतापगढ़ में महिला एवं बाल विकास विभाग के नवीन उपनिदेशक कार्यालय का उद्घाटन किया",
    "state": "Rajasthan",
    "link": "https://dipr.rajasthan.gov.in/press-release-detail/243956/85",
    "content": "वीआईपी श्रेणी वीआईपी व्यक्ति उप श्रेणी कार्यक्रम प्रेस विज्ञप्ति स्तर राज्य स्तरीय विभाग जिला चित्तौड़गढ़ जिला जिला चित्तौड़गढ़, जिला जयपुर\nजयपुर,15 जून। राजस्व मंत्री श्री हेमंत मीणा एवं सांसद श्री सीपी जोशी ने सोमवार को प्रतापगढ़ शहर में महिला एवं बाल विकास विभाग के नवीन उपनिदेशक कार्यालय का फीता काटकर उद्घाटन किया।\nश्री हेमंत मीणा ने कहा कि राज्य सरकार महिलाओं एवं बच्चों के सर्वांगीण विकास के लिए प्रतिबद्ध है तथा विभागीय योजनाओं का लाभ अंतिम व्यक्ति तक पहुंचाने के लिए लगातार प्रयास किए जा रहे हैं। उन्होंने विभागीय कार्मिकों को संवेदनशीलता एवं समर्पण भाव से कार्य करने को कहा।\nसांसद श्री सीपी जोशी ने कहा कि महिला एवं बाल विकास विभाग समाज के कमजोर एवं जरूरतमंद वर्गों के उत्थान में महत्वपूर्ण भूमिका निभा रहा है। नवीन कार्यालय भवन से विभागीय कार्यों में गति आएगी तथा आमजन व कार्मिकों को बेहतर सुविधाएं उपलब्ध होंगी।\nकार्यक्रम में आईसीडीएस के श्री करण सिंह, उप निदेशक श्री प्रेम सिंह तथा महिला अधिकारिता विभाग की सहायक निदेशक श्रीमती नेहा माथुर भी उपस्थित रहे।\n———\nतुलसीराम/ब्रजेश\nडाउनलोड"
  }
]